{
  "type": "output",
  "name": "stringSum",
  "connectors": [
    {
      "type": "connector--output",
      "accept": "connector--input"
    },
    {
      "type": "connector--input",
      "accept": "connector--output",
      "acceptType": [
        "String"
      ],
      "suggestedBloqs": [
        "string",
        "selectVariable"
      ],
      "name": "e0b095ba-4c3f-4a1b-b9fa-9eb1d61ab9de"
    },
    {
      "type": "connector--input",
      "accept": "connector--output",
      "acceptType": [
        "String"
      ],
      "suggestedBloqs": [
        "string",
        "selectVariable"
      ],
      "name": "622c6187-81da-43a7-8aff-f19220030e14"
    }
  ],
  "bloqClass": "bloq-string-sum",
  "content": [
    [
      {
        "bloqInputId": "ARG1",
        "alias": "bloqInput",
        "acceptType": [
          "String"
        ],
        "suggestedBloqs": [
          "string",
          "selectVariable"
        ],
        "name": "e0b095ba-4c3f-4a1b-b9fa-9eb1d61ab9de"
      },
      {
        "alias": "text",
        "value": "+"
      },
      {
        "bloqInputId": "ARG2",
        "alias": "bloqInput",
        "acceptType": [
          "String"
        ],
        "suggestedBloqs": [
          "string",
          "selectVariable"
        ],
        "name": "622c6187-81da-43a7-8aff-f19220030e14"
      }
    ]
  ],
  "code": "String({ARG1})+String({ARG2})",
  "returnType": {
    "type": "simple",
    "value": "String"
  },
  "arduino": {
    "code": "String({ARG1})+String({ARG2})"
  },
  "python": {
    "codeLines": [
      {
        "code": "Bloque \"stringSum\" no preparado para generar código python"
      }
    ]
  }
}